py2ts/__init__.py
py2ts/builder.py
py2ts/config.py
py2ts/data.py
py2ts/generate.py
py2ts/py.typed
py2ts/utils.py
python2ts-0.6.1.dist-info/METADATA
python2ts-0.6.1.dist-info/WHEEL
python2ts-0.6.1.dist-info/licenses/LICENSE
python2ts-0.6.1.dist-info/RECORD
